gitlab_version_bumper/__init__.py
gitlab_version_bumper/cli.py
gitlab_version_bumper-1.0.0.dist-info/LICENSE
gitlab_version_bumper-1.0.0.dist-info/METADATA
gitlab_version_bumper-1.0.0.dist-info/WHEEL
gitlab_version_bumper-1.0.0.dist-info/entry_points.txt
gitlab_version_bumper-1.0.0.dist-info/top_level.txt
gitlab_version_bumper-1.0.0.dist-info/RECORD
