Metadata-Version: 2.2
Name: gitlab-version-bumper
Version: 1.0.0
Summary: Python CLI tool to determine current version in GitLab pipelines.
Author-email: Elias Rosch <eliasrosch@googlemail.com>
License: MIT
Project-URL: Homepage, https://gitlab.com/EvilEli/gitlab-version-bumper
Project-URL: Documentation, https://gitlab.com/EvilEli/gitlab-version-bumper
Project-URL: Repository, https://gitlab.com/EvilEli/gitlab-version-bumper.git
Project-URL: Changelog, https://gitlab.com/EvilEli/gitlab-version-bumper
Classifier: Programming Language :: Python :: 3
Classifier: License :: OSI Approved :: MIT License
Classifier: Operating System :: OS Independent
Requires-Python: >=3.9
License-File: LICENSE
Requires-Dist: semver
Requires-Dist: click
